{
  "lastUpdate": "2025-09-30T07:36:04.746Z",
  "opportunities": [
    {
      "token": "XLM",
      "buyExchange": 4,
      "sellExchange": 1,
      "avgFundingBuy": -0.012237000000000001,
      "avgFundingSell": 0.00125,
      "apr": 118.14612000000001,
      "buyOI": 675420.9065,
      "sellOI": 8389264.042848,
      "buyVolume": 278580.47945000004,
      "sellVolume": 2306892.2046900014,
      "buyBid": 0.3674,
      "buyAsk": 0.3677,
      "buyMidPrice": 0.36755000000000004,
      "sellBid": 0.36822,
      "sellAsk": 0.368328,
      "sellMidPrice": 0.368274,
      "spread": 0.0014141963557246801
    },
    {
      "token": "SOL",
      "buyExchange": 4,
      "sellExchange": 1,
      "avgFundingBuy": -0.0060940000000000005,
      "avgFundingSell": 0.00125,
      "apr": 64.33344000000001,
      "buyOI": 70941498.957,
      "sellOI": 1302432551.949277,
      "buyVolume": 1336884984.666,
      "sellVolume": 826608826.1407996,
      "buyBid": 209.47,
      "buyAsk": 209.48,
      "buyMidPrice": 209.475,
      "sellBid": 209.57,
      "sellAsk": 209.5888,
      "sellMidPrice": 209.5794,
      "spread": 0.0004296352873782863
    },
    {
      "token": "BCH",
      "buyExchange": 4,
      "sellExchange": 1,
      "avgFundingBuy": -0.0007199999999999999,
      "avgFundingSell": 0.00125,
      "apr": 17.2572,
      "buyOI": 143226.5103,
      "sellOI": 5164192.083765,
      "buyVolume": 555430.3712999999,
      "sellVolume": 723676.3639600003,
      "buyBid": 556.9,
      "buyAsk": 557.3,
      "buyMidPrice": 557.0999999999999,
      "sellBid": 557.35,
      "sellAsk": 557.465,
      "sellMidPrice": 557.4075,
      "spread": 0.00008971828458652111
    }
  ]
}